<?xml version="1.0" encoding="utf-8"?>
<!DOCTYPE hibernate-mapping PUBLIC "-//Hibernate/Hibernate Mapping DTD 3.0//EN"
"http://hibernate.sourceforge.net/hibernate-mapping-3.0.dtd">
<!-- 
    Mapping file autogenerated by MyEclipse - Hibernate Tools
-->
<hibernate-mapping>
    <class name="org.net9.redbud.storage.hibernate.publicinfo.Publicinfo" table="publicinfo" >
        <id name="id" type="java.lang.Integer">
            <column name="id" />
            <generator class="native" />
        </id>
        <property name="infotitle" type="java.lang.String">
            <column name="infotitle" length="45" not-null="true" />
        </property>
        <property name="infocontent" type="java.lang.String">
            <column name="infocontent" length="65535" not-null="true" />
        </property>
        <property name="ownerid" type="java.lang.Integer">
            <column name="ownerid" not-null="true" />
        </property>
        <property name="ownercatename" type="java.lang.String">
            <column name="ownercatename" length="45" not-null="true" />
        </property>
        <property name="publishtime" type="java.lang.Long">
            <column name="publishtime" not-null="true" />
        </property>
        <property name="approvetime" type="java.lang.Long">
            <column name="approvetime" not-null="true" />
        </property>
        <property name="approvestatus" type="java.lang.Integer">
            <column name="approvestatus" not-null="true" />
        </property>
        <set name="publicinfologins" inverse="true">
            <key>
                <column name="publicinfoid" not-null="true" />
            </key>
            <one-to-many class="org.net9.redbud.storage.hibernate.publicinfologin.Publicinfologin" />
        </set>
    </class>
</hibernate-mapping>
